.gitignore
COPYING
MANIFEST.in
README.rst
setup.py
vcversioner.py
version.txt
bin/git-author
git_author/__init__.py
git_author/__main__.py
git_author/_version.py
git_author.egg-info/PKG-INFO
git_author.egg-info/SOURCES.txt
git_author.egg-info/dependency_links.txt
git_author.egg-info/requires.txt
git_author.egg-info/top_level.txt