Metadata-Version: 2.1
Name: git-author
Version: 1.1.0
Summary: git-author, a git command for managing multiple authors
Home-page: https://github.com/cfelder/git-author
Author: Christian Felder
Author-email: webmaster@bsm-felder.de
License: LGPL-3.0+
Platform: UNKNOWN
Classifier: Development Status :: 3 - Alpha
Classifier: Intended Audience :: Developers
Classifier: License :: OSI Approved :: GNU General Public License v3 or later (GPLv3+)
Classifier: Natural Language :: English
Classifier: Operating System :: OS Independent
Classifier: Programming Language :: Python
Classifier: Programming Language :: Python :: 2
Classifier: Programming Language :: Python :: 3
Classifier: Topic :: Software Development
Classifier: Topic :: Software Development :: Version Control
Classifier: Topic :: Software Development :: Version Control :: Git
License-File: COPYING
